{
  "_meta": {
    "version": "1.0.0",
    "created": "2026-04-26",
    "source": "USDA FoodData Central, SR Legacy + Foundation Foods",
    "license": "Public Domain (US Government work)",
    "url": "https://fdc.nal.usda.gov/",
    "note": "Faz 3 polish batch 5 (oturum 21) - top 201-300 frequency, hand-curated. Coverage hedef %97 -> %98+. Alias entry'leri ayni USDA verisi farkli yazimla."
  },
  "items": [
    { "name": "yaban mersini", "fdcId": 171711, "caloriesPer100g": 57, "proteinPer100g": 0.74, "carbsPer100g": 14.49, "fatPer100g": 0.33, "sugarPer100g": 9.96, "fiberPer100g": 2.4, "sodiumPer100g": 1, "satFatPer100g": 0.028, "glycemicIndex": 53, "defaultUnit": "g", "gramsPerUnit": 148, "source": "USDA FDC 171711 (Blueberries, raw)" },
    { "name": "parmesan peyniri", "fdcId": 173404, "caloriesPer100g": 415, "proteinPer100g": 37.86, "carbsPer100g": 4.06, "fatPer100g": 27.84, "sugarPer100g": 0.8, "fiberPer100g": 0, "sodiumPer100g": 1696, "satFatPer100g": 17.7, "glycemicIndex": null, "defaultUnit": "g", "gramsPerUnit": 5, "source": "USDA FDC 173404 (Parmesan, grated)" },
    { "name": "parmesan", "fdcId": 173404, "caloriesPer100g": 415, "proteinPer100g": 37.86, "carbsPer100g": 4.06, "fatPer100g": 27.84, "sugarPer100g": 0.8, "fiberPer100g": 0, "sodiumPer100g": 1696, "satFatPer100g": 17.7, "glycemicIndex": null, "defaultUnit": "g", "gramsPerUnit": 5, "source": "USDA FDC 173404 (alias of parmesan peyniri)" },
    { "name": "somon fileto", "fdcId": 175167, "caloriesPer100g": 208, "proteinPer100g": 20.42, "carbsPer100g": 0, "fatPer100g": 13.42, "sugarPer100g": 0, "fiberPer100g": 0, "sodiumPer100g": 59, "satFatPer100g": 3.05, "glycemicIndex": null, "defaultUnit": "g", "gramsPerUnit": 100, "source": "USDA FDC 175167 (Atlantic salmon, raw)" },
    { "name": "cheddar peyniri", "fdcId": 173414, "caloriesPer100g": 404, "proteinPer100g": 22.87, "carbsPer100g": 3.09, "fatPer100g": 33.31, "sugarPer100g": 0.48, "fiberPer100g": 0, "sodiumPer100g": 653, "satFatPer100g": 18.87, "glycemicIndex": null, "defaultUnit": "g", "gramsPerUnit": 28, "source": "USDA FDC 173414 (Cheddar cheese)" },
    { "name": "cheddar", "fdcId": 173414, "caloriesPer100g": 404, "proteinPer100g": 22.87, "carbsPer100g": 3.09, "fatPer100g": 33.31, "sugarPer100g": 0.48, "fiberPer100g": 0, "sodiumPer100g": 653, "satFatPer100g": 18.87, "glycemicIndex": null, "defaultUnit": "g", "gramsPerUnit": 28, "source": "USDA FDC 173414 (alias of cheddar peyniri)" },
    { "name": "sandviç ekmeği", "fdcId": 174929, "caloriesPer100g": 270, "proteinPer100g": 9.0, "carbsPer100g": 49.0, "fatPer100g": 3.5, "sugarPer100g": 5.0, "fiberPer100g": 2.5, "sodiumPer100g": 491, "satFatPer100g": 0.7, "glycemicIndex": 75, "defaultUnit": "g", "gramsPerUnit": 28, "source": "USDA FDC 174929 (Bread, sandwich)" },
    { "name": "kinoa", "fdcId": 168874, "caloriesPer100g": 368, "proteinPer100g": 14.12, "carbsPer100g": 64.16, "fatPer100g": 6.07, "sugarPer100g": 0, "fiberPer100g": 7.0, "sodiumPer100g": 5, "satFatPer100g": 0.706, "glycemicIndex": 53, "defaultUnit": "g", "gramsPerUnit": 170, "source": "USDA FDC 168874 (Quinoa, raw)" },
    { "name": "karnabahar", "fdcId": 169986, "caloriesPer100g": 25, "proteinPer100g": 1.92, "carbsPer100g": 4.97, "fatPer100g": 0.28, "sugarPer100g": 1.91, "fiberPer100g": 2.0, "sodiumPer100g": 30, "satFatPer100g": 0.13, "glycemicIndex": null, "defaultUnit": "g", "gramsPerUnit": 575, "source": "USDA FDC 169986 (Cauliflower, raw)" },
    { "name": "pudra şekeri", "fdcId": 169656, "caloriesPer100g": 389, "proteinPer100g": 0, "carbsPer100g": 99.8, "fatPer100g": 0, "sugarPer100g": 97.78, "fiberPer100g": 0, "sodiumPer100g": 2, "satFatPer100g": 0, "glycemicIndex": 100, "defaultUnit": "g", "gramsPerUnit": 4, "source": "USDA FDC 169656 (Powdered sugar)" },
    { "name": "çavdar ekmeği", "fdcId": 174905, "caloriesPer100g": 259, "proteinPer100g": 8.5, "carbsPer100g": 48.3, "fatPer100g": 3.3, "sugarPer100g": 3.85, "fiberPer100g": 5.8, "sodiumPer100g": 603, "satFatPer100g": 0.6, "glycemicIndex": 50, "defaultUnit": "g", "gramsPerUnit": 32, "source": "USDA FDC 174905 (Rye bread)" },
    { "name": "bisküvi kırıntısı", "fdcId": 175003, "caloriesPer100g": 480, "proteinPer100g": 5.0, "carbsPer100g": 70.0, "fatPer100g": 20.0, "sugarPer100g": 30.0, "fiberPer100g": 2.0, "sodiumPer100g": 350, "satFatPer100g": 7.0, "glycemicIndex": 70, "defaultUnit": "g", "gramsPerUnit": 80, "source": "USDA proxy (Cookie crumb, sweet biscuit)" },
    { "name": "ayran", "fdcId": 781084, "caloriesPer100g": 36, "proteinPer100g": 3.3, "carbsPer100g": 4.0, "fatPer100g": 0.9, "sugarPer100g": 4.0, "fiberPer100g": 0, "sodiumPer100g": 320, "satFatPer100g": 0.6, "glycemicIndex": null, "defaultUnit": "ml", "gramsPerUnit": 1.03, "source": "USDA proxy (Buttermilk drink, salted)" },
    { "name": "ayva", "fdcId": 169136, "caloriesPer100g": 57, "proteinPer100g": 0.4, "carbsPer100g": 15.3, "fatPer100g": 0.1, "sugarPer100g": 0, "fiberPer100g": 1.9, "sodiumPer100g": 4, "satFatPer100g": 0.013, "glycemicIndex": 35, "defaultUnit": "g", "gramsPerUnit": 92, "source": "USDA FDC 169136 (Quince, raw)" },
    { "name": "kurut", "fdcId": 781119, "caloriesPer100g": 410, "proteinPer100g": 35.0, "carbsPer100g": 35.0, "fatPer100g": 17.0, "sugarPer100g": 30.0, "fiberPer100g": 0, "sodiumPer100g": 850, "satFatPer100g": 11.0, "glycemicIndex": null, "defaultUnit": "g", "gramsPerUnit": 10, "source": "USDA proxy (Dried yogurt ball, salted)" },
    { "name": "salça", "fdcId": 170457, "caloriesPer100g": 82, "proteinPer100g": 4.32, "carbsPer100g": 18.91, "fatPer100g": 0.47, "sugarPer100g": 12.21, "fiberPer100g": 4.1, "sodiumPer100g": 59, "satFatPer100g": 0.069, "glycemicIndex": null, "defaultUnit": "g", "gramsPerUnit": 16, "source": "USDA FDC 170457 (Tomato paste)" },
    { "name": "hindistan cevizi", "fdcId": 170169, "caloriesPer100g": 354, "proteinPer100g": 3.33, "carbsPer100g": 15.23, "fatPer100g": 33.49, "sugarPer100g": 6.23, "fiberPer100g": 9.0, "sodiumPer100g": 20, "satFatPer100g": 29.7, "glycemicIndex": 45, "defaultUnit": "g", "gramsPerUnit": 80, "source": "USDA FDC 170169 (Coconut meat, raw)" },
    { "name": "mısır yarması", "fdcId": 170283, "caloriesPer100g": 384, "proteinPer100g": 8.12, "carbsPer100g": 80.5, "fatPer100g": 3.86, "sugarPer100g": 0.64, "fiberPer100g": 7.3, "sodiumPer100g": 6, "satFatPer100g": 0.539, "glycemicIndex": 70, "defaultUnit": "g", "gramsPerUnit": 122, "source": "USDA FDC 170283 (Cornmeal, coarse)" },
    { "name": "bazlama", "fdcId": 174985, "caloriesPer100g": 274, "proteinPer100g": 9.0, "carbsPer100g": 56.0, "fatPer100g": 1.0, "sugarPer100g": 1.5, "fiberPer100g": 2.0, "sodiumPer100g": 593, "satFatPer100g": 0.2, "glycemicIndex": null, "defaultUnit": "g", "gramsPerUnit": 80, "source": "USDA FDC 174985 (Flatbread, similar)" },
    { "name": "gochujang", "fdcId": 175011, "caloriesPer100g": 174, "proteinPer100g": 6.0, "carbsPer100g": 27.0, "fatPer100g": 4.6, "sugarPer100g": 12.0, "fiberPer100g": 6.0, "sodiumPer100g": 2300, "satFatPer100g": 0.7, "glycemicIndex": null, "defaultUnit": "g", "gramsPerUnit": 18, "source": "USDA proxy (Korean fermented chili paste)" },
    { "name": "dana döş", "fdcId": 169511, "caloriesPer100g": 285, "proteinPer100g": 17.49, "carbsPer100g": 0, "fatPer100g": 23.39, "sugarPer100g": 0, "fiberPer100g": 0, "sodiumPer100g": 65, "satFatPer100g": 9.27, "glycemicIndex": null, "defaultUnit": "g", "gramsPerUnit": 113, "source": "USDA FDC 169511 (Beef brisket, raw)" },
    { "name": "mısır tanesi", "fdcId": 169998, "caloriesPer100g": 86, "proteinPer100g": 3.27, "carbsPer100g": 18.7, "fatPer100g": 1.35, "sugarPer100g": 6.26, "fiberPer100g": 2.0, "sodiumPer100g": 15, "satFatPer100g": 0.197, "glycemicIndex": 52, "defaultUnit": "g", "gramsPerUnit": 154, "source": "USDA FDC 169998 (Sweet corn, raw)" },
    { "name": "asma yaprağı", "fdcId": 170076, "caloriesPer100g": 69, "proteinPer100g": 4.27, "carbsPer100g": 11.71, "fatPer100g": 1.97, "sugarPer100g": 6.31, "fiberPer100g": 11.0, "sodiumPer100g": 2150, "satFatPer100g": 0.301, "glycemicIndex": null, "defaultUnit": "g", "gramsPerUnit": 4, "source": "USDA FDC 170076 (Grape leaves, canned)" },
    { "name": "haşlanmış barbunya", "fdcId": 173746, "caloriesPer100g": 143, "proteinPer100g": 9.01, "carbsPer100g": 26.22, "fatPer100g": 0.65, "sugarPer100g": 0.34, "fiberPer100g": 9.0, "sodiumPer100g": 1, "satFatPer100g": 0.137, "glycemicIndex": 39, "defaultUnit": "g", "gramsPerUnit": 171, "source": "USDA FDC 173746 (Pinto beans, cooked)" },
    { "name": "domates sosu", "fdcId": 170947, "caloriesPer100g": 24, "proteinPer100g": 1.07, "carbsPer100g": 5.39, "fatPer100g": 0.11, "sugarPer100g": 4.04, "fiberPer100g": 1.4, "sodiumPer100g": 358, "satFatPer100g": 0.013, "glycemicIndex": null, "defaultUnit": "g", "gramsPerUnit": 245, "source": "USDA FDC 170947 (Tomato sauce, canned)" },
    { "name": "kuskus", "fdcId": 169728, "caloriesPer100g": 112, "proteinPer100g": 3.79, "carbsPer100g": 23.22, "fatPer100g": 0.16, "sugarPer100g": 0.09, "fiberPer100g": 1.4, "sodiumPer100g": 5, "satFatPer100g": 0.024, "glycemicIndex": 65, "defaultUnit": "g", "gramsPerUnit": 157, "source": "USDA FDC 169728 (Couscous, cooked)" },
    { "name": "taze kekik", "fdcId": 170938, "caloriesPer100g": 101, "proteinPer100g": 5.56, "carbsPer100g": 24.45, "fatPer100g": 1.68, "sugarPer100g": 0, "fiberPer100g": 14.0, "sodiumPer100g": 9, "satFatPer100g": 0.467, "glycemicIndex": null, "defaultUnit": "g", "gramsPerUnit": 2, "source": "USDA FDC 170938 (Thyme, fresh)" },
    { "name": "tatlı kırmızı biber", "fdcId": 170108, "caloriesPer100g": 31, "proteinPer100g": 1.0, "carbsPer100g": 6.0, "fatPer100g": 0.3, "sugarPer100g": 4.2, "fiberPer100g": 2.1, "sodiumPer100g": 4, "satFatPer100g": 0.027, "glycemicIndex": null, "defaultUnit": "g", "gramsPerUnit": 119, "source": "USDA FDC 170108 (Bell pepper, red, raw)" },
    { "name": "yeşil erik", "fdcId": 169949, "caloriesPer100g": 46, "proteinPer100g": 0.7, "carbsPer100g": 11.42, "fatPer100g": 0.28, "sugarPer100g": 9.92, "fiberPer100g": 1.4, "sodiumPer100g": 0, "satFatPer100g": 0.017, "glycemicIndex": 39, "defaultUnit": "g", "gramsPerUnit": 66, "source": "USDA FDC 169949 (Plum, green, raw)" },
    { "name": "biberiye", "fdcId": 171328, "caloriesPer100g": 131, "proteinPer100g": 3.31, "carbsPer100g": 20.7, "fatPer100g": 5.86, "sugarPer100g": 0, "fiberPer100g": 14.1, "sodiumPer100g": 26, "satFatPer100g": 2.838, "glycemicIndex": null, "defaultUnit": "g", "gramsPerUnit": 1.7, "source": "USDA FDC 171328 (Rosemary, fresh)" },
    { "name": "haşlanmış börülce", "fdcId": 174273, "caloriesPer100g": 116, "proteinPer100g": 7.73, "carbsPer100g": 20.76, "fatPer100g": 0.53, "sugarPer100g": 3.31, "fiberPer100g": 6.5, "sodiumPer100g": 4, "satFatPer100g": 0.142, "glycemicIndex": 33, "defaultUnit": "g", "gramsPerUnit": 165, "source": "USDA FDC 174273 (Cowpea, black-eyed, cooked)" },
    { "name": "köy ekmeği", "fdcId": 174903, "caloriesPer100g": 261, "proteinPer100g": 9.0, "carbsPer100g": 53.0, "fatPer100g": 1.5, "sugarPer100g": 4.0, "fiberPer100g": 2.5, "sodiumPer100g": 590, "satFatPer100g": 0.3, "glycemicIndex": 73, "defaultUnit": "g", "gramsPerUnit": 50, "source": "USDA FDC 174903 (Bread, white, country style)" },
    { "name": "kuru domates", "fdcId": 170458, "caloriesPer100g": 258, "proteinPer100g": 14.11, "carbsPer100g": 55.76, "fatPer100g": 2.97, "sugarPer100g": 37.59, "fiberPer100g": 12.3, "sodiumPer100g": 2095, "satFatPer100g": 0.43, "glycemicIndex": null, "defaultUnit": "g", "gramsPerUnit": 2, "source": "USDA FDC 170458 (Sun-dried tomato)" },
    { "name": "dut pekmezi", "fdcId": 169658, "caloriesPer100g": 290, "proteinPer100g": 0, "carbsPer100g": 74.7, "fatPer100g": 0.1, "sugarPer100g": 74.7, "fiberPer100g": 0, "sodiumPer100g": 37, "satFatPer100g": 0.034, "glycemicIndex": 70, "defaultUnit": "g", "gramsPerUnit": 20, "source": "USDA proxy (Mulberry molasses, similar to grape molasses)" },
    { "name": "siyah çay", "fdcId": 173468, "caloriesPer100g": 1, "proteinPer100g": 0, "carbsPer100g": 0.3, "fatPer100g": 0, "sugarPer100g": 0, "fiberPer100g": 0, "sodiumPer100g": 3, "satFatPer100g": 0, "glycemicIndex": null, "defaultUnit": "ml", "gramsPerUnit": 1.0, "source": "USDA FDC 173468 (Tea, black, brewed)" },
    { "name": "siyah fasulye", "fdcId": 173734, "caloriesPer100g": 341, "proteinPer100g": 21.6, "carbsPer100g": 62.36, "fatPer100g": 1.42, "sugarPer100g": 2.12, "fiberPer100g": 15.5, "sodiumPer100g": 5, "satFatPer100g": 0.366, "glycemicIndex": 30, "defaultUnit": "g", "gramsPerUnit": 194, "source": "USDA FDC 173734 (Black beans, raw)" },
    { "name": "hamsi", "fdcId": 175168, "caloriesPer100g": 131, "proteinPer100g": 20.35, "carbsPer100g": 0, "fatPer100g": 4.84, "sugarPer100g": 0, "fiberPer100g": 0, "sodiumPer100g": 88, "satFatPer100g": 1.282, "glycemicIndex": null, "defaultUnit": "g", "gramsPerUnit": 100, "source": "USDA FDC 175168 (alias of hamsi fileto)" },
    { "name": "ananas", "fdcId": 169124, "caloriesPer100g": 50, "proteinPer100g": 0.54, "carbsPer100g": 13.12, "fatPer100g": 0.12, "sugarPer100g": 9.85, "fiberPer100g": 1.4, "sodiumPer100g": 1, "satFatPer100g": 0.009, "glycemicIndex": 66, "defaultUnit": "g", "gramsPerUnit": 165, "source": "USDA FDC 169124 (Pineapple, raw)" },
    { "name": "kuzu kıyma", "fdcId": 174501, "caloriesPer100g": 282, "proteinPer100g": 16.56, "carbsPer100g": 0, "fatPer100g": 23.41, "sugarPer100g": 0, "fiberPer100g": 0, "sodiumPer100g": 65, "satFatPer100g": 9.92, "glycemicIndex": null, "defaultUnit": "g", "gramsPerUnit": 113, "source": "USDA FDC 174501 (Lamb, ground)" },
    { "name": "turunç suyu", "fdcId": 169098, "caloriesPer100g": 47, "proteinPer100g": 0.94, "carbsPer100g": 11.0, "fatPer100g": 0.12, "sugarPer100g": 9.0, "fiberPer100g": 0.2, "sodiumPer100g": 1, "satFatPer100g": 0.015, "glycemicIndex": null, "defaultUnit": "ml", "gramsPerUnit": 1.04, "source": "USDA proxy (Bitter orange juice, similar to orange juice)" },
    { "name": "yulaf ezmesi", "fdcId": 173904, "caloriesPer100g": 379, "proteinPer100g": 13.15, "carbsPer100g": 67.7, "fatPer100g": 6.52, "sugarPer100g": 0.99, "fiberPer100g": 10.1, "sodiumPer100g": 6, "satFatPer100g": 1.117, "glycemicIndex": 55, "defaultUnit": "g", "gramsPerUnit": 81, "source": "USDA FDC 173904 (Oats, whole rolled)" },
    { "name": "ananas suyu", "fdcId": 169126, "caloriesPer100g": 53, "proteinPer100g": 0.36, "carbsPer100g": 12.87, "fatPer100g": 0.12, "sugarPer100g": 9.98, "fiberPer100g": 0.2, "sodiumPer100g": 2, "satFatPer100g": 0.014, "glycemicIndex": 50, "defaultUnit": "ml", "gramsPerUnit": 1.05, "source": "USDA FDC 169126 (Pineapple juice)" },
    { "name": "şeker şurubu", "fdcId": 169655, "caloriesPer100g": 290, "proteinPer100g": 0, "carbsPer100g": 75.0, "fatPer100g": 0, "sugarPer100g": 75.0, "fiberPer100g": 0, "sodiumPer100g": 5, "satFatPer100g": 0, "glycemicIndex": 100, "defaultUnit": "ml", "gramsPerUnit": 1.32, "source": "USDA proxy (Simple syrup)" },
    { "name": "arpa", "fdcId": 170284, "caloriesPer100g": 352, "proteinPer100g": 9.91, "carbsPer100g": 77.72, "fatPer100g": 1.16, "sugarPer100g": 0.8, "fiberPer100g": 15.6, "sodiumPer100g": 9, "satFatPer100g": 0.244, "glycemicIndex": 28, "defaultUnit": "g", "gramsPerUnit": 200, "source": "USDA FDC 170284 (Barley, pearled, raw)" },
    { "name": "tel kadayıf", "fdcId": 175040, "caloriesPer100g": 365, "proteinPer100g": 9.0, "carbsPer100g": 70.0, "fatPer100g": 4.0, "sugarPer100g": 1.5, "fiberPer100g": 2.0, "sodiumPer100g": 500, "satFatPer100g": 1.0, "glycemicIndex": null, "defaultUnit": "g", "gramsPerUnit": 100, "source": "USDA proxy (Kataifi shredded phyllo)" },
    { "name": "adaçayı", "fdcId": 171324, "caloriesPer100g": 315, "proteinPer100g": 10.63, "carbsPer100g": 60.73, "fatPer100g": 12.75, "sugarPer100g": 1.71, "fiberPer100g": 40.3, "sodiumPer100g": 11, "satFatPer100g": 7.034, "glycemicIndex": null, "defaultUnit": "g", "gramsPerUnit": 0.7, "source": "USDA FDC 171324 (Sage, ground)" },
    { "name": "kırmızı erik", "fdcId": 169949, "caloriesPer100g": 46, "proteinPer100g": 0.7, "carbsPer100g": 11.42, "fatPer100g": 0.28, "sugarPer100g": 9.92, "fiberPer100g": 1.4, "sodiumPer100g": 0, "satFatPer100g": 0.017, "glycemicIndex": 39, "defaultUnit": "g", "gramsPerUnit": 66, "source": "USDA FDC 169949 (Plum, raw)" },
    { "name": "koruk suyu", "fdcId": 173469, "caloriesPer100g": 8, "proteinPer100g": 0.5, "carbsPer100g": 1.6, "fatPer100g": 0, "sugarPer100g": 0, "fiberPer100g": 0, "sodiumPer100g": 5, "satFatPer100g": 0, "glycemicIndex": null, "defaultUnit": "ml", "gramsPerUnit": 1.0, "source": "USDA proxy (Verjus, unripe grape juice)" },
    { "name": "kültür mantarı", "fdcId": 169251, "caloriesPer100g": 22, "proteinPer100g": 3.09, "carbsPer100g": 3.26, "fatPer100g": 0.34, "sugarPer100g": 1.98, "fiberPer100g": 1.0, "sodiumPer100g": 5, "satFatPer100g": 0.05, "glycemicIndex": null, "defaultUnit": "g", "gramsPerUnit": 70, "source": "USDA FDC 169251 (White mushroom, raw)" },
    { "name": "zeytin", "fdcId": 169094, "caloriesPer100g": 115, "proteinPer100g": 0.84, "carbsPer100g": 6.26, "fatPer100g": 10.68, "sugarPer100g": 0, "fiberPer100g": 3.2, "sodiumPer100g": 735, "satFatPer100g": 1.415, "glycemicIndex": null, "defaultUnit": "g", "gramsPerUnit": 4, "source": "USDA FDC 169094 (Olives, mixed - alias of siyah zeytin)" },
    { "name": "turp", "fdcId": 169276, "caloriesPer100g": 16, "proteinPer100g": 0.68, "carbsPer100g": 3.4, "fatPer100g": 0.1, "sugarPer100g": 1.86, "fiberPer100g": 1.6, "sodiumPer100g": 39, "satFatPer100g": 0.032, "glycemicIndex": null, "defaultUnit": "g", "gramsPerUnit": 116, "source": "USDA FDC 169276 (Radish, raw)" },
    { "name": "otlu peynir", "fdcId": 173420, "caloriesPer100g": 264, "proteinPer100g": 14.21, "carbsPer100g": 4.09, "fatPer100g": 21.28, "sugarPer100g": 4.09, "fiberPer100g": 0, "sodiumPer100g": 1116, "satFatPer100g": 14.946, "glycemicIndex": null, "defaultUnit": "g", "gramsPerUnit": 28, "source": "USDA FDC 173420 (Feta-style cheese with herbs proxy)" },
    { "name": "tulum peyniri", "fdcId": 173420, "caloriesPer100g": 350, "proteinPer100g": 22.0, "carbsPer100g": 2.0, "fatPer100g": 28.0, "sugarPer100g": 1.0, "fiberPer100g": 0, "sodiumPer100g": 1500, "satFatPer100g": 16.0, "glycemicIndex": null, "defaultUnit": "g", "gramsPerUnit": 28, "source": "USDA proxy (Tulum cheese, aged sheep cheese)" },
    { "name": "yumurta akı", "fdcId": 172183, "caloriesPer100g": 52, "proteinPer100g": 10.9, "carbsPer100g": 0.73, "fatPer100g": 0.17, "sugarPer100g": 0.71, "fiberPer100g": 0, "sodiumPer100g": 166, "satFatPer100g": 0, "glycemicIndex": null, "defaultUnit": "g", "gramsPerUnit": 33, "source": "USDA FDC 172183 (Egg white)" },
    { "name": "kuzu eti", "fdcId": 174506, "caloriesPer100g": 282, "proteinPer100g": 16.6, "carbsPer100g": 0, "fatPer100g": 23.4, "sugarPer100g": 0, "fiberPer100g": 0, "sodiumPer100g": 70, "satFatPer100g": 10.2, "glycemicIndex": null, "defaultUnit": "g", "gramsPerUnit": 113, "source": "USDA FDC 174506 (alias of kuzu kuşbaşı)" },
    { "name": "hardaliye", "fdcId": 173469, "caloriesPer100g": 15, "proteinPer100g": 0.2, "carbsPer100g": 3.5, "fatPer100g": 0.1, "sugarPer100g": 2.5, "fiberPer100g": 0, "sodiumPer100g": 50, "satFatPer100g": 0, "glycemicIndex": null, "defaultUnit": "ml", "gramsPerUnit": 1.0, "source": "USDA proxy (Mustard fermented grape juice)" },
    { "name": "rom", "fdcId": 174552, "caloriesPer100g": 231, "proteinPer100g": 0, "carbsPer100g": 0, "fatPer100g": 0, "sugarPer100g": 0, "fiberPer100g": 0, "sodiumPer100g": 1, "satFatPer100g": 0, "glycemicIndex": null, "defaultUnit": "ml", "gramsPerUnit": 0.93, "source": "USDA FDC 174552 (Rum, distilled spirit)" },
    { "name": "beyaz rom", "fdcId": 174552, "caloriesPer100g": 231, "proteinPer100g": 0, "carbsPer100g": 0, "fatPer100g": 0, "sugarPer100g": 0, "fiberPer100g": 0, "sodiumPer100g": 1, "satFatPer100g": 0, "glycemicIndex": null, "defaultUnit": "ml", "gramsPerUnit": 0.93, "source": "USDA FDC 174552 (alias of rom)" },
    { "name": "haşlanmış beyaz fasulye", "fdcId": 173742, "caloriesPer100g": 139, "proteinPer100g": 9.73, "carbsPer100g": 25.09, "fatPer100g": 0.35, "sugarPer100g": 0.35, "fiberPer100g": 6.3, "sodiumPer100g": 6, "satFatPer100g": 0.09, "glycemicIndex": 35, "defaultUnit": "g", "gramsPerUnit": 179, "source": "USDA FDC 173742 (alias of haşlanmış kuru fasulye)" },
    { "name": "kuru fasulye", "fdcId": 173741, "caloriesPer100g": 333, "proteinPer100g": 23.36, "carbsPer100g": 60.27, "fatPer100g": 0.85, "sugarPer100g": 2.11, "fiberPer100g": 15.2, "sodiumPer100g": 16, "satFatPer100g": 0.219, "glycemicIndex": 35, "defaultUnit": "g", "gramsPerUnit": 196, "source": "USDA FDC 173741 (White beans, raw)" },
    { "name": "pide ekmeği", "fdcId": 174903, "caloriesPer100g": 275, "proteinPer100g": 9.07, "carbsPer100g": 55.7, "fatPer100g": 1.2, "sugarPer100g": 1.36, "fiberPer100g": 2.2, "sodiumPer100g": 536, "satFatPer100g": 0.176, "glycemicIndex": 68, "defaultUnit": "g", "gramsPerUnit": 60, "source": "USDA FDC 174903 (Pita bread)" },
    { "name": "yer fıstığı ezmesi", "fdcId": 174299, "caloriesPer100g": 588, "proteinPer100g": 24.95, "carbsPer100g": 21.55, "fatPer100g": 50.39, "sugarPer100g": 9.21, "fiberPer100g": 5.6, "sodiumPer100g": 459, "satFatPer100g": 8.211, "glycemicIndex": 14, "defaultUnit": "g", "gramsPerUnit": 16, "source": "USDA FDC 174299 (Peanut butter)" },
    { "name": "nori", "fdcId": 168459, "caloriesPer100g": 35, "proteinPer100g": 5.81, "carbsPer100g": 5.11, "fatPer100g": 0.28, "sugarPer100g": 0.5, "fiberPer100g": 0.3, "sodiumPer100g": 48, "satFatPer100g": 0.073, "glycemicIndex": null, "defaultUnit": "g", "gramsPerUnit": 3, "source": "USDA FDC 168459 (Nori, dried seaweed)" },
    { "name": "votka", "fdcId": 174552, "caloriesPer100g": 231, "proteinPer100g": 0, "carbsPer100g": 0, "fatPer100g": 0, "sugarPer100g": 0, "fiberPer100g": 0, "sodiumPer100g": 1, "satFatPer100g": 0, "glycemicIndex": null, "defaultUnit": "ml", "gramsPerUnit": 0.94, "source": "USDA FDC 174552 (Vodka)" },
    { "name": "dolmalık biber", "fdcId": 170428, "caloriesPer100g": 26, "proteinPer100g": 0.99, "carbsPer100g": 6.03, "fatPer100g": 0.17, "sugarPer100g": 4.2, "fiberPer100g": 1.7, "sodiumPer100g": 4, "satFatPer100g": 0.058, "glycemicIndex": null, "defaultUnit": "g", "gramsPerUnit": 119, "source": "USDA FDC 170428 (Bell pepper, green, raw)" },
    { "name": "haşlanmış pancar", "fdcId": 169145, "caloriesPer100g": 44, "proteinPer100g": 1.68, "carbsPer100g": 9.96, "fatPer100g": 0.18, "sugarPer100g": 7.96, "fiberPer100g": 2.0, "sodiumPer100g": 77, "satFatPer100g": 0.027, "glycemicIndex": 64, "defaultUnit": "g", "gramsPerUnit": 170, "source": "USDA FDC 169145 (Beet, boiled)" },
    { "name": "kuru biber", "fdcId": 170103, "caloriesPer100g": 282, "proteinPer100g": 14.14, "carbsPer100g": 53.99, "fatPer100g": 12.89, "sugarPer100g": 10.34, "fiberPer100g": 34.9, "sodiumPer100g": 68, "satFatPer100g": 2.142, "glycemicIndex": null, "defaultUnit": "g", "gramsPerUnit": 5, "source": "USDA FDC 170103 (Dried red pepper)" },
    { "name": "salatalık turşusu", "fdcId": 169301, "caloriesPer100g": 12, "proteinPer100g": 0.43, "carbsPer100g": 2.41, "fatPer100g": 0.13, "sugarPer100g": 1.06, "fiberPer100g": 1.2, "sodiumPer100g": 1208, "satFatPer100g": 0.034, "glycemicIndex": null, "defaultUnit": "g", "gramsPerUnit": 30, "source": "USDA FDC 169301 (Cucumber, pickled)" },
    { "name": "vanilin", "fdcId": 169675, "caloriesPer100g": 288, "proteinPer100g": 0.06, "carbsPer100g": 12.65, "fatPer100g": 0.06, "sugarPer100g": 12.65, "fiberPer100g": 0, "sodiumPer100g": 9, "satFatPer100g": 0.01, "glycemicIndex": null, "defaultUnit": "g", "gramsPerUnit": 4, "source": "USDA FDC 169675 (Vanilla extract)" },
    { "name": "ekşi mayalı ekmek", "fdcId": 174903, "caloriesPer100g": 289, "proteinPer100g": 11.65, "carbsPer100g": 56.6, "fatPer100g": 1.95, "sugarPer100g": 0.95, "fiberPer100g": 2.4, "sodiumPer100g": 600, "satFatPer100g": 0.42, "glycemicIndex": 54, "defaultUnit": "g", "gramsPerUnit": 50, "source": "USDA proxy (Sourdough bread)" },
    { "name": "gül suyu", "fdcId": 174194, "caloriesPer100g": 0, "proteinPer100g": 0, "carbsPer100g": 0, "fatPer100g": 0, "sugarPer100g": 0, "fiberPer100g": 0, "sodiumPer100g": 0, "satFatPer100g": 0, "glycemicIndex": null, "defaultUnit": "ml", "gramsPerUnit": 1.0, "source": "USDA proxy (Rose water = water)" },
    { "name": "levrek fileto", "fdcId": 173707, "caloriesPer100g": 97, "proteinPer100g": 18.43, "carbsPer100g": 0, "fatPer100g": 2.0, "sugarPer100g": 0, "fiberPer100g": 0, "sodiumPer100g": 68, "satFatPer100g": 0.512, "glycemicIndex": null, "defaultUnit": "g", "gramsPerUnit": 100, "source": "USDA FDC 173707 (Sea bass, raw)" },
    { "name": "tonik", "fdcId": 174843, "caloriesPer100g": 34, "proteinPer100g": 0, "carbsPer100g": 8.81, "fatPer100g": 0, "sugarPer100g": 8.81, "fiberPer100g": 0, "sodiumPer100g": 12, "satFatPer100g": 0, "glycemicIndex": null, "defaultUnit": "ml", "gramsPerUnit": 1.04, "source": "USDA FDC 174843 (Tonic water)" },
    { "name": "haşlanmış fasulye", "fdcId": 173742, "caloriesPer100g": 139, "proteinPer100g": 9.73, "carbsPer100g": 25.09, "fatPer100g": 0.35, "sugarPer100g": 0.35, "fiberPer100g": 6.3, "sodiumPer100g": 6, "satFatPer100g": 0.09, "glycemicIndex": 35, "defaultUnit": "g", "gramsPerUnit": 179, "source": "USDA FDC 173742 (alias generic cooked beans)" },
    { "name": "rakı", "fdcId": 174552, "caloriesPer100g": 245, "proteinPer100g": 0, "carbsPer100g": 0.2, "fatPer100g": 0, "sugarPer100g": 0, "fiberPer100g": 0, "sodiumPer100g": 1, "satFatPer100g": 0, "glycemicIndex": null, "defaultUnit": "ml", "gramsPerUnit": 0.93, "source": "USDA proxy (Anise spirit)" },
    { "name": "sosis", "fdcId": 174562, "caloriesPer100g": 301, "proteinPer100g": 12.46, "carbsPer100g": 1.5, "fatPer100g": 27.27, "sugarPer100g": 0.74, "fiberPer100g": 0, "sodiumPer100g": 848, "satFatPer100g": 9.22, "glycemicIndex": null, "defaultUnit": "g", "gramsPerUnit": 50, "source": "USDA FDC 174562 (Sausage, frankfurter)" },
    { "name": "mısır ekmeği", "fdcId": 175038, "caloriesPer100g": 330, "proteinPer100g": 7.16, "carbsPer100g": 51.07, "fatPer100g": 11.07, "sugarPer100g": 14.1, "fiberPer100g": 1.5, "sodiumPer100g": 651, "satFatPer100g": 1.926, "glycemicIndex": 70, "defaultUnit": "g", "gramsPerUnit": 60, "source": "USDA FDC 175038 (Cornbread)" },
    { "name": "yenibahar", "fdcId": 170913, "caloriesPer100g": 263, "proteinPer100g": 6.09, "carbsPer100g": 72.12, "fatPer100g": 8.69, "sugarPer100g": 0, "fiberPer100g": 21.6, "sodiumPer100g": 77, "satFatPer100g": 2.55, "glycemicIndex": null, "defaultUnit": "g", "gramsPerUnit": 1.9, "source": "USDA FDC 170913 (Allspice, ground)" },
    { "name": "feta peyniri", "fdcId": 173420, "caloriesPer100g": 264, "proteinPer100g": 14.21, "carbsPer100g": 4.09, "fatPer100g": 21.28, "sugarPer100g": 4.09, "fiberPer100g": 0, "sodiumPer100g": 1116, "satFatPer100g": 14.946, "glycemicIndex": null, "defaultUnit": "g", "gramsPerUnit": 28, "source": "USDA FDC 173420 (Feta cheese)" },
    { "name": "baget ekmek", "fdcId": 174904, "caloriesPer100g": 274, "proteinPer100g": 8.7, "carbsPer100g": 56.0, "fatPer100g": 1.6, "sugarPer100g": 2.0, "fiberPer100g": 2.5, "sodiumPer100g": 632, "satFatPer100g": 0.36, "glycemicIndex": 95, "defaultUnit": "g", "gramsPerUnit": 35, "source": "USDA FDC 174904 (Baguette, French bread)" },
    { "name": "dolmalık fıstık", "fdcId": 170591, "caloriesPer100g": 673, "proteinPer100g": 13.69, "carbsPer100g": 13.08, "fatPer100g": 68.37, "sugarPer100g": 3.59, "fiberPer100g": 3.7, "sodiumPer100g": 2, "satFatPer100g": 4.899, "glycemicIndex": null, "defaultUnit": "g", "gramsPerUnit": 4, "source": "USDA FDC 170591 (Pine nuts)" },
    { "name": "çam fıstığı", "fdcId": 170591, "caloriesPer100g": 673, "proteinPer100g": 13.69, "carbsPer100g": 13.08, "fatPer100g": 68.37, "sugarPer100g": 3.59, "fiberPer100g": 3.7, "sodiumPer100g": 2, "satFatPer100g": 4.899, "glycemicIndex": null, "defaultUnit": "g", "gramsPerUnit": 4, "source": "USDA FDC 170591 (alias of dolmalık fıstık)" },
    { "name": "lahana turşusu", "fdcId": 169280, "caloriesPer100g": 19, "proteinPer100g": 0.91, "carbsPer100g": 4.28, "fatPer100g": 0.14, "sugarPer100g": 1.78, "fiberPer100g": 2.9, "sodiumPer100g": 661, "satFatPer100g": 0.034, "glycemicIndex": null, "defaultUnit": "g", "gramsPerUnit": 142, "source": "USDA FDC 169280 (Sauerkraut)" },
    { "name": "mozzarella", "fdcId": 173417, "caloriesPer100g": 280, "proteinPer100g": 22.17, "carbsPer100g": 2.19, "fatPer100g": 22.35, "sugarPer100g": 1.0, "fiberPer100g": 0, "sodiumPer100g": 627, "satFatPer100g": 13.15, "glycemicIndex": null, "defaultUnit": "g", "gramsPerUnit": 28, "source": "USDA FDC 173417 (Mozzarella, low-moisture)" },
    { "name": "badem unu", "fdcId": 170567, "caloriesPer100g": 575, "proteinPer100g": 21.15, "carbsPer100g": 21.55, "fatPer100g": 49.93, "sugarPer100g": 4.35, "fiberPer100g": 12.5, "sodiumPer100g": 1, "satFatPer100g": 3.802, "glycemicIndex": 25, "defaultUnit": "g", "gramsPerUnit": 96, "source": "USDA FDC 170567 (Almond flour)" },
    { "name": "sucuk", "fdcId": 174562, "caloriesPer100g": 380, "proteinPer100g": 22.0, "carbsPer100g": 2.0, "fatPer100g": 32.0, "sugarPer100g": 0, "fiberPer100g": 0, "sodiumPer100g": 1500, "satFatPer100g": 13.0, "glycemicIndex": null, "defaultUnit": "g", "gramsPerUnit": 28, "source": "USDA proxy (Sucuk, Turkish dry sausage)" },
    { "name": "karışık ot", "fdcId": 170937, "caloriesPer100g": 270, "proteinPer100g": 9.0, "carbsPer100g": 50.0, "fatPer100g": 7.0, "sugarPer100g": 1.0, "fiberPer100g": 22.0, "sodiumPer100g": 50, "satFatPer100g": 2.0, "glycemicIndex": null, "defaultUnit": "g", "gramsPerUnit": 2, "source": "USDA proxy (Mixed dried herbs)" },
    { "name": "misket limonu suyu", "fdcId": 169115, "caloriesPer100g": 25, "proteinPer100g": 0.42, "carbsPer100g": 8.42, "fatPer100g": 0.07, "sugarPer100g": 1.37, "fiberPer100g": 0.4, "sodiumPer100g": 2, "satFatPer100g": 0.008, "glycemicIndex": null, "defaultUnit": "ml", "gramsPerUnit": 1.04, "source": "USDA FDC 169115 (Lime juice)" },
    { "name": "mısır tortilla", "fdcId": 173801, "caloriesPer100g": 218, "proteinPer100g": 5.7, "carbsPer100g": 44.64, "fatPer100g": 2.85, "sugarPer100g": 1.41, "fiberPer100g": 6.3, "sodiumPer100g": 45, "satFatPer100g": 0.395, "glycemicIndex": 50, "defaultUnit": "g", "gramsPerUnit": 26, "source": "USDA FDC 173801 (Corn tortilla)" },
    { "name": "viski", "fdcId": 174552, "caloriesPer100g": 250, "proteinPer100g": 0, "carbsPer100g": 0.1, "fatPer100g": 0, "sugarPer100g": 0, "fiberPer100g": 0, "sodiumPer100g": 1, "satFatPer100g": 0, "glycemicIndex": null, "defaultUnit": "ml", "gramsPerUnit": 0.94, "source": "USDA proxy (Whisky, distilled spirit)" },
    { "name": "elma suyu", "fdcId": 173947, "caloriesPer100g": 46, "proteinPer100g": 0.1, "carbsPer100g": 11.3, "fatPer100g": 0.13, "sugarPer100g": 9.62, "fiberPer100g": 0.2, "sodiumPer100g": 4, "satFatPer100g": 0.022, "glycemicIndex": 40, "defaultUnit": "ml", "gramsPerUnit": 1.05, "source": "USDA FDC 173947 (Apple juice)" },
    { "name": "kimchi", "fdcId": 169394, "caloriesPer100g": 15, "proteinPer100g": 1.1, "carbsPer100g": 2.4, "fatPer100g": 0.5, "sugarPer100g": 1.1, "fiberPer100g": 1.6, "sodiumPer100g": 498, "satFatPer100g": 0.07, "glycemicIndex": null, "defaultUnit": "g", "gramsPerUnit": 150, "source": "USDA FDC 169394 (Kimchi, fermented)" },
    { "name": "haşlanmış pirinç", "fdcId": 169757, "caloriesPer100g": 130, "proteinPer100g": 2.69, "carbsPer100g": 28.17, "fatPer100g": 0.28, "sugarPer100g": 0.05, "fiberPer100g": 0.4, "sodiumPer100g": 1, "satFatPer100g": 0.077, "glycemicIndex": 73, "defaultUnit": "g", "gramsPerUnit": 158, "source": "USDA FDC 169757 (White rice, cooked)" },
    { "name": "dövme buğday", "fdcId": 175040, "caloriesPer100g": 342, "proteinPer100g": 12.29, "carbsPer100g": 70.59, "fatPer100g": 1.83, "sugarPer100g": 0.41, "fiberPer100g": 18.1, "sodiumPer100g": 17, "satFatPer100g": 0.302, "glycemicIndex": 50, "defaultUnit": "g", "gramsPerUnit": 100, "source": "USDA FDC 175040 (Cracked wheat)" },
    { "name": "tortilla", "fdcId": 174946, "caloriesPer100g": 304, "proteinPer100g": 8.2, "carbsPer100g": 50.45, "fatPer100g": 7.13, "sugarPer100g": 1.86, "fiberPer100g": 3.0, "sodiumPer100g": 580, "satFatPer100g": 1.748, "glycemicIndex": 72, "defaultUnit": "g", "gramsPerUnit": 49, "source": "USDA FDC 174946 (Wheat tortilla)" },
    { "name": "köz patlıcan", "fdcId": 169228, "caloriesPer100g": 35, "proteinPer100g": 0.83, "carbsPer100g": 8.73, "fatPer100g": 0.23, "sugarPer100g": 3.2, "fiberPer100g": 2.5, "sodiumPer100g": 2, "satFatPer100g": 0.044, "glycemicIndex": null, "defaultUnit": "g", "gramsPerUnit": 200, "source": "USDA FDC 169228 (Eggplant, roasted)" },
    { "name": "portakal kabuğu rendesi", "fdcId": 169095, "caloriesPer100g": 97, "proteinPer100g": 1.5, "carbsPer100g": 25.0, "fatPer100g": 0.2, "sugarPer100g": 0, "fiberPer100g": 10.6, "sodiumPer100g": 3, "satFatPer100g": 0.024, "glycemicIndex": null, "defaultUnit": "g", "gramsPerUnit": 2, "source": "USDA FDC 169095 (alias of portakal kabuğu)" },
    { "name": "haşlanmış mısır", "fdcId": 169998, "caloriesPer100g": 86, "proteinPer100g": 3.27, "carbsPer100g": 18.7, "fatPer100g": 1.35, "sugarPer100g": 6.26, "fiberPer100g": 2.0, "sodiumPer100g": 1, "satFatPer100g": 0.197, "glycemicIndex": 52, "defaultUnit": "g", "gramsPerUnit": 154, "source": "USDA FDC 169998 (Sweet corn, cooked, alias)" },
    { "name": "bayat ekmek içi", "fdcId": 174928, "caloriesPer100g": 395, "proteinPer100g": 13.35, "carbsPer100g": 71.98, "fatPer100g": 5.3, "sugarPer100g": 5.83, "fiberPer100g": 4.5, "sodiumPer100g": 732, "satFatPer100g": 1.286, "glycemicIndex": null, "defaultUnit": "g", "gramsPerUnit": 30, "source": "USDA FDC 174928 (Bread crumbs, dry)" },
    { "name": "sarımsak tozu", "fdcId": 171325, "caloriesPer100g": 331, "proteinPer100g": 16.55, "carbsPer100g": 72.73, "fatPer100g": 0.73, "sugarPer100g": 2.43, "fiberPer100g": 9.0, "sodiumPer100g": 60, "satFatPer100g": 0.249, "glycemicIndex": null, "defaultUnit": "g", "gramsPerUnit": 3, "source": "USDA FDC 171325 (Garlic powder)" },
    { "name": "limon kabuğu rendesi", "fdcId": 169097, "caloriesPer100g": 47, "proteinPer100g": 1.5, "carbsPer100g": 16.0, "fatPer100g": 0.3, "sugarPer100g": 4.17, "fiberPer100g": 10.6, "sodiumPer100g": 6, "satFatPer100g": 0.039, "glycemicIndex": null, "defaultUnit": "g", "gramsPerUnit": 2, "source": "USDA FDC 169097 (alias of limon kabuğu)" }
  ]
}
