[
  {
    "slug": "sbiten",
    "servingSuggestion": "Sbiteni sıcak verin, kupayı portakal dilimi ve tarçın çubuğuyla tamamlayın."
  },
  {
    "slug": "scallion-pancake-cin-sokak-usulu",
    "servingSuggestion": "Dilimleri sıcak sunun, yanına siyah sirke dip sosu ve acı yağ koyun."
  },
  {
    "slug": "scotch-broth-ingiliz-usulu",
    "servingSuggestion": "Çorbayı sıcak verin, yanına arpalı ekmek ve tereyağı koyun."
  },
  {
    "slug": "scotch-egg-ingiliz-usulu",
    "servingSuggestion": "Yumurtaları ılık sunun, yanına hardal ve turşu koyun."
  },
  {
    "slug": "sebze-corbasi",
    "servingSuggestion": "Çorbayı sıcak verin, üstüne zeytinyağı gezdirip yanında limon sunun."
  },
  {
    "slug": "sebzeli-goce-kofte-nevsehir-usulu",
    "servingSuggestion": "Köfteleri sıcak sunun, yanına sarımsaklı yoğurt ve salata koyun."
  },
  {
    "slug": "sebzeli-guvec",
    "servingSuggestion": "Güveci sıcak verin, yanına köy ekmeği ve yoğurt koyun."
  },
  {
    "slug": "sebzeli-noodle",
    "servingSuggestion": "Noodleı sıcak sunun, üstüne susam ve taze soğan serpin."
  },
  {
    "slug": "sebzeli-paella",
    "servingSuggestion": "Paellayı sıcak verin, yanına limon dilimi ve alioli koyun."
  },
  {
    "slug": "sebzeli-spring-roll",
    "servingSuggestion": "Rollları ılık sunun, yanına tatlı acı sos ve lime koyun."
  },
  {
    "slug": "sebzeli-tarhonya-pilavi-macaristan-usulu",
    "servingSuggestion": "Pilavı sıcak verin, yanına yoğurt ve salatalık turşusu koyun."
  },
  {
    "slug": "seco-de-res-peru-usulu",
    "servingSuggestion": "Yemeği sıcak sunun, yanına pirinç ve salsa criolla koyun."
  },
  {
    "slug": "seffa-kuzey-afrika-usulu",
    "servingSuggestion": "Seffayı ılık verin, üstüne tarçın serpip yanında badem sunun."
  },
  {
    "slug": "sehriye-corbasi",
    "servingSuggestion": "Çorbayı sıcak sunun, üstüne karabiber çekip yanında limon verin."
  },
  {
    "slug": "sembusek-tostu-mardin-usulu",
    "servingSuggestion": "Tostu sıcak verin, yanına ayran ve turşu koyun."
  },
  {
    "slug": "semizotlu-borulce-salatasi-manisa-usulu",
    "servingSuggestion": "Salatayı serin sunun, üstüne zeytinyağı gezdirip limon sıkın."
  },
  {
    "slug": "semizotlu-nohut-corbasi-manisa-usulu",
    "servingSuggestion": "Çorbayı sıcak verin, üstüne pul biberli yağ gezdirin."
  },
  {
    "slug": "semla",
    "servingSuggestion": "Semlayı ılık verin, üstüne pudra şekeri serpip kahveyle sunun."
  },
  {
    "slug": "sernik-kavanozu-polonya-usulu",
    "servingSuggestion": "Kavanozu soğuk sunun, üstüne yaban mersini ve bisküvi kırığı ekleyin."
  },
  {
    "slug": "sernik-krakowski",
    "servingSuggestion": "Dilimleri soğuk verin, yanına çilek sosu ya da sade krema koyun."
  },
  {
    "slug": "sernik-na-zimno-cilekli-polonya-usulu",
    "servingSuggestion": "Tatlıyı soğuk sunun, üstüne çilek dilimleri ve nane ekleyin."
  },
  {
    "slug": "sesame-balls",
    "tipNote": "Topları orta sıcak yağda çevirmek susamın eşit kızarmasını kolaylaştırır.",
    "servingSuggestion": "Susam toplarını sıcak verin, yanına yasemin çayı koyun."
  },
  {
    "slug": "sesame-noodles-cin-soguk-usulu",
    "servingSuggestion": "Erişteyi serin sunun, üstüne susam ve taze soğan serpin."
  },
  {
    "slug": "sevketibostan-yemegi",
    "tipNote": "Şevketibostanı ayıklarken kök kısmını iyi temizlemek acılığı dengeler.",
    "servingSuggestion": "Yemeği sıcak verin, yanına limon dilimi ve ekmek koyun."
  },
  {
    "slug": "sevketibostanli-bulgur-pilavi-ayvalik-usulu",
    "servingSuggestion": "Pilavı sıcak sunun, yanına yoğurt ve limon dilimi koyun."
  },
  {
    "slug": "shawarma-pilavi",
    "servingSuggestion": "Pilavı sıcak verin, yanına sarımsaklı yoğurt ve turşu koyun."
  },
  {
    "slug": "shchi",
    "tipNote": "Lahanayı son bölümde eklemek çorbada diri dokuyu korumaya yardımcı olur.",
    "servingSuggestion": "Çorbayı sıcak sunun, üstüne dereotu serpip ekşi krema ekleyin."
  },
  {
    "slug": "shepherds-pie-ingiliz-usulu",
    "servingSuggestion": "Dilimleri sıcak verin, yanına bezelye ve gravy sos koyun."
  },
  {
    "slug": "shire-toffee-puding-ingiliz-usulu",
    "servingSuggestion": "Tatlıyı ılık sunun, üstüne ekstra toffee sos ve krema koyun."
  },
  {
    "slug": "shish-barak",
    "servingSuggestion": "Mantıları sıcak verin, üstüne kuru nane serpip yanında sunun."
  },
  {
    "slug": "sinh-to-bo",
    "servingSuggestion": "İçeceği çok soğuk verin, üstüne avokado küpleri ekleyip hemen sunun."
  },
  {
    "slug": "sini-koftesi",
    "servingSuggestion": "Köfteyi sıcak sunun, yanına maydanoz salatası ve limon koyun."
  },
  {
    "slug": "sivas-hingeli",
    "servingSuggestion": "Hıngeli sıcak verin, üstüne tereyağı gezdirip yanında yoğurt sunun."
  },
  {
    "slug": "siyah-fasulye-corbasi-kuba-usulu",
    "servingSuggestion": "Çorbayı sıcak sunun, yanına pirinç ve lime dilimi koyun."
  },
  {
    "slug": "siyah-fasulyeli-balkabagi-corbasi-brezilya-usulu",
    "servingSuggestion": "Çorbayı sıcak verin, üstüne kişniş serpip yanında lime sunun."
  },
  {
    "slug": "siyah-fasulyeli-pilav-bowl-kuba-usulu",
    "servingSuggestion": "Bowlu sıcak sunun, yanına avokado ve lime dilimi koyun."
  },
  {
    "slug": "siyez-unlu-elma-keki-kastamonu-usulu",
    "servingSuggestion": "Keki ılık verin, üstüne tarçın serpip yanında çay sunun."
  },
  {
    "slug": "skagen-yumurtali-acik-sandvic-isvec-usulu",
    "servingSuggestion": "Sandviçi soğuk sunun, üstüne dereotu serpip yanında limon verin."
  },
  {
    "slug": "skordalia",
    "tipNote": "Patates sıcakken ezilirse skordalia daha pürüzsüz bir kıvam alır.",
    "servingSuggestion": "Ezmeyi serin verin, yanına kızarmış ekmek ve zeytin koyun."
  },
  {
    "slug": "smetanali-mantarli-arpa-tavasi-rus-usulu",
    "servingSuggestion": "Tavayı sıcak sunun, üstüne dereotu serpip yanında turşu verin."
  },
  {
    "slug": "sogan-kebabi-tepsi-kilis-usulu",
    "servingSuggestion": "Kebabı sıcak verin, yanına lavaş ve sumaklı maydanoz koyun."
  },
  {
    "slug": "soganli-fasulye-tursu-kavurmasi-giresun-usulu",
    "servingSuggestion": "Kavurmayı sıcak sunun, yanına mısır ekmeği ve yoğurt koyun."
  },
  {
    "slug": "solyanka-rus-usulu",
    "servingSuggestion": "Çorbayı sıcak verin, üstüne ekşi krema koyup yanında limon sunun."
  },
  {
    "slug": "som-tam-misirli-tay-usulu",
    "servingSuggestion": "Salatayı serin verin, yanına lime dilimi ve kavrulmuş fıstık koyun."
  },
  {
    "slug": "somloi-kup-tatlisi-macar-usulu",
    "servingSuggestion": "Kupu soğuk sunun, üstüne kakao serpip biraz krema ekleyin."
  },
  {
    "slug": "somonlu-arpa-sehriye-tava-isvec-usulu",
    "servingSuggestion": "Tavayı sıcak verin, üstüne dereotu serpip yanında limon sunun."
  },
  {
    "slug": "somonlu-sebzeli-udon-tava-japon-usulu",
    "servingSuggestion": "Udonu sıcak sunun, üstüne susam serpip yanında lime verin."
  },
  {
    "slug": "sopa-de-fideo",
    "tipNote": "Erişteyi önce yağda kızartmak çorbaya daha derin bir tat verir."
  },
  {
    "slug": "sopa-de-fideo-verde-meksika-usulu",
    "servingSuggestion": "Çorbayı sıcak verin, üstüne kişniş serpip yanında lime sunun."
  },
  {
    "slug": "sopa-de-frijoles-negros-kuba-usulu",
    "servingSuggestion": "Çorbayı sıcak sunun, yanına pirinç ve lime dilimi koyun."
  },
  {
    "slug": "sopa-de-lima",
    "servingSuggestion": "Çorbayı sıcak verin, üstüne tortilla şeritleri serpip lime ekleyin."
  },
  {
    "slug": "sopa-de-tortilla-meksika-usulu",
    "servingSuggestion": "Çorbayı sıcak sunun, üstüne tortilla şeritleri ve avokado ekleyin."
  }
]
